{
    "sourceFile": "4/4.c",
    "activeCommit": 0,
    "commits": [
        {
            "activePatchIndex": 5,
            "patches": [
                {
                    "date": 1635699043182,
                    "content": "Index: \n===================================================================\n--- \n+++ \n"
                },
                {
                    "date": 1635699219945,
                    "content": "Index: \n===================================================================\n--- \n+++ \n@@ -37,9 +37,10 @@\n         scanf(\"%f\", &m1);\r\n         printf(\"\\nMarks Achieved in Final M1: %.1f\", m1);\r\n         total = internals + m1;\r\n         printf(\"\\nTotal = %.1f\", total);\r\n-        (total >= 50 && total < 60) ? (grade = 6) : (total >= 60 && total < 70) ? (grade = 7)\r\n+        (total >= 50 && total < 60) ? (grade = 6) :\r\n+         (total >= 60 && total < 70) ? (grade = 7)\r\n                                                 : (total >= 70 && total < 80)   ? (grade = 8)\r\n                                                 : (total >= 80 && total < 90)   ? (grade = 9)\r\n                                                 : (total >= 90)                 ? (grade = 10)\r\n                                                                                 : (grade = 4.5);\r\n"
                },
                {
                    "date": 1635699243260,
                    "content": "Index: \n===================================================================\n--- \n+++ \n@@ -37,13 +37,12 @@\n         scanf(\"%f\", &m1);\r\n         printf(\"\\nMarks Achieved in Final M1: %.1f\", m1);\r\n         total = internals + m1;\r\n         printf(\"\\nTotal = %.1f\", total);\r\n-        (total >= 50 && total < 60) ? (grade = 6) :\r\n-         (total >= 60 && total < 70) ? (grade = 7)\r\n+        (total >= 50 && total < 60) ? (grade = 6) : (total >= 60 && total < 70) ? (grade = 7)\r\n                                                 : (total >= 70 && total < 80)   ? (grade = 8)\r\n                                                 : (total >= 80 && total < 90)   ? (grade = 9)\r\n-                                                : (total >= 90)                 ? (grade = 10)\r\n+                                                : (total >= 90)                 ? (grade = 10);\r\n                                                                                 : (grade = 4.5);\r\n         printf(\"\\nGrade = %d\", grade);\r\n         credit_points = courseCreditTotal * grade;\r\n         mgpa = credit_points / courseCreditTotal;\r\n"
                },
                {
                    "date": 1635699279807,
                    "content": "Index: \n===================================================================\n--- \n+++ \n@@ -40,10 +40,10 @@\n         printf(\"\\nTotal = %.1f\", total);\r\n         (total >= 50 && total < 60) ? (grade = 6) : (total >= 60 && total < 70) ? (grade = 7)\r\n                                                 : (total >= 70 && total < 80)   ? (grade = 8)\r\n                                                 : (total >= 80 && total < 90)   ? (grade = 9)\r\n-                                                : (total >= 90)                 ? (grade = 10);\r\n-                                                                                : (grade = 4.5);\r\n+                                                : (total >= 90)                 ? (grade = 10)\r\n+                                                                                : (grade = 4.);\r\n         printf(\"\\nGrade = %d\", grade);\r\n         credit_points = courseCreditTotal * grade;\r\n         mgpa = credit_points / courseCreditTotal;\r\n         printf(\"\\nYour MGPA for Mat %d = %.1f\", mat_num, mgpa);\r\n"
                },
                {
                    "date": 1635699288002,
                    "content": "Index: \n===================================================================\n--- \n+++ \n@@ -41,9 +41,9 @@\n         (total >= 50 && total < 60) ? (grade = 6) : (total >= 60 && total < 70) ? (grade = 7)\r\n                                                 : (total >= 70 && total < 80)   ? (grade = 8)\r\n                                                 : (total >= 80 && total < 90)   ? (grade = 9)\r\n                                                 : (total >= 90)                 ? (grade = 10)\r\n-                                                                                : ();\r\n+                                                                                : (a);\r\n         printf(\"\\nGrade = %d\", grade);\r\n         credit_points = courseCreditTotal * grade;\r\n         mgpa = credit_points / courseCreditTotal;\r\n         printf(\"\\nYour MGPA for Mat %d = %.1f\", mat_num, mgpa);\r\n"
                },
                {
                    "date": 1635699709044,
                    "content": "Index: \n===================================================================\n--- \n+++ \n@@ -89,6 +89,6 @@\n     default:\r\n         printf(\"Invalid Input!\\a\");\r\n         break;\r\n     }\r\n-}\r\n+ }\r\n }\n\\ No newline at end of file\n"
                }
            ],
            "date": 1635699043182,
            "name": "Commit-0",
            "content": "#include <stdio.h>\r\n#include <stdlib.h>\r\nint main()\r\n{\r\n    int option, mat_num, courses, courseCredit, courseCreditTotal, grade, credit_points, matCreditTotal = 0, total_mats, matCredit = 0;\r\n    printf(\"\\n\\n*********************************************************\");\r\n    printf(\"\\nWelcome to CS.CODE.IN's Credit Score Analyser\\n\");\r\n    printf(\"*********************************************************\\n\");\r\n    printf(\"\\nChoose from below Options:- \");\r\n    printf(\"\\n\\nA) Press 1 to Calculate MGPA\");\r\n    printf(\"\\nB) Press 2 to Calculate CGPA\");\r\n    printf(\"\\nE) Press 0 to Exit \");\r\n    printf(\"\\n\\nEnter your Input:  \");\r\n    scanf(\"%d\", &option);\r\n\r\n    switch ((int)option)\r\n    {\r\n    case 1:\r\n    {\r\n        float internals, m1, total, mgpa;\r\n        printf(\"\\nEnter MAT Number:  \");\r\n        scanf(\"%d\", &mat_num);\r\n        printf(\"\\nEnter Number of Courses:  \");\r\n        scanf(\"%d\", &courses);\r\n        for (int i = 1; i <= courses; i++)\r\n        {\r\n            printf(\"\\nEnter credits alloted for course %d: \", i);\r\n            scanf(\"%d\", &courseCredit);\r\n            courseCreditTotal += courseCredit;\r\n        }\r\n        printf(\"Total Credits = %d\", courseCreditTotal);\r\n\r\n        printf(\"\\nEnter Marks Achieved in Internals: \");\r\n        scanf(\"%f\", &internals);\r\n        printf(\"\\nMarks Achieved in Internals: %.1f\", internals);\r\n        printf(\"\\nEnter Marks Achieved in Final M1: \");\r\n        scanf(\"%f\", &m1);\r\n        printf(\"\\nMarks Achieved in Final M1: %.1f\", m1);\r\n        total = internals + m1;\r\n        printf(\"\\nTotal = %.1f\", total);\r\n        (total >= 50 && total < 60) ? (grade = 6) : (total >= 60 && total < 70) ? (grade = 7)\r\n                                                : (total >= 70 && total < 80)   ? (grade = 8)\r\n                                                : (total >= 80 && total < 90)   ? (grade = 9)\r\n                                                : (total >= 90)                 ? (grade = 10)\r\n                                                                                : (grade = 4.5);\r\n        printf(\"\\nGrade = %d\", grade);\r\n        credit_points = courseCreditTotal * grade;\r\n        mgpa = credit_points / courseCreditTotal;\r\n        printf(\"\\nYour MGPA for Mat %d = %.1f\", mat_num, mgpa);\r\n    }\r\n    break;\r\n\r\n    case 2:\r\n    {\r\n\r\n        float total2, mgpa2, cgpa;\r\n        printf(\"\\nEnter Total Number of MAT's: \");\r\n        scanf(\"%d\", &total_mats);\r\n        if (total_mats <= 12)\r\n        {\r\n            for (int i = 1; i <= total_mats; i++)\r\n            {\r\n                printf(\"\\nEnter total Credits for MAT %d: \", i);\r\n                scanf(\"%d\", &matCredit);\r\n                printf(\"\\nEnter MGPA for MAT %d: \", i);\r\n                scanf(\"%f\", &mgpa2);\r\n                total2 += matCredit * mgpa2;\r\n                matCreditTotal += matCredit;\r\n                cgpa = total2 / matCredit;\r\n            }\r\n            printf(\"\\nTotal Credits into MGPA = %.1f\", total2);\r\n            printf(\"\\nTotal MAT Credits = %d\", matCreditTotal);\r\n\r\n            printf(\"\\nYour CGPA is %.1f (until mat %d)\", cgpa, total_mats);\r\n        }\r\n        else\r\n        {\r\n            printf(\"Invalid Input!\");\r\n        }\r\n    }\r\n    break;\r\n    case 0:\r\n    {\r\n        exit(0);\r\n    }\r\n    default:\r\n        printf(\"Invalid Input!\\a\");\r\n        break;\r\n    }\r\n}"
        }
    ]
}